fimpy/__init__.py
fimpy/fimpy.py
fimpy/utilities.py
fimpy/alignment/__init__.py
fimpy/loading/__init__.py
fimpy/loading/planewise.py
fimpy/loading/utilities.py
fimpy/loading/volumetric.py
fimpy/pipeline/__init__.py
fimpy/pipeline/common.py
fimpy/pipeline/general.py
fimpy/roi_extraction/__init__.py
fimpy/roi_extraction/anatomical.py
fimpy/roi_extraction/corr_algorithms.py
fimpy/roi_extraction/local_correlations.py
fimpy/roi_extraction/merging.py
fimpy-0.1.4.dist-info/AUTHORS.rst
fimpy-0.1.4.dist-info/LICENSE
fimpy-0.1.4.dist-info/METADATA
fimpy-0.1.4.dist-info/WHEEL
fimpy-0.1.4.dist-info/top_level.txt
fimpy-0.1.4.dist-info/RECORD
