Metadata-Version: 2.1
Name: fimpy
Version: 0.1.4
Summary: A python package for parallelizable processing of fluorescent imaging data
Home-page: https://github.com/portugueslab/fimpy
Author: Luigi Petrucco & Vilim Stih @portugueslab
Author-email: luigi.petrucco@gmail.com
License: GNU General Public License v3
Keywords: fimpy
Platform: UNKNOWN
Classifier: Development Status :: 2 - Pre-Alpha
Classifier: Intended Audience :: Developers
Classifier: License :: OSI Approved :: GNU General Public License v3 (GPLv3)
Classifier: Natural Language :: English
Classifier: Programming Language :: Python :: 3
Classifier: Programming Language :: Python :: 3.5
Classifier: Programming Language :: Python :: 3.6
Classifier: Programming Language :: Python :: 3.7
Classifier: Programming Language :: Python :: 3.8
Requires-Python: >=3.5
Requires-Dist: numpy
Requires-Dist: numba
Requires-Dist: scipy
Requires-Dist: scikit-image
Requires-Dist: imageio
Requires-Dist: h5py
Requires-Dist: flammkuchen
Requires-Dist: lightparam
Requires-Dist: split-dataset
